restcord/__init__.py
restcord/ban.py
restcord/channel.py
restcord/channel_client.py
restcord/client.py
restcord/emoji.py
restcord/emoji_client.py
restcord/errors.py
restcord/guild.py
restcord/guild_client.py
restcord/http.py
restcord/invite.py
restcord/invite_client.py
restcord/member.py
restcord/message.py
restcord/permissions.py
restcord/role.py
restcord/snowflake.py
restcord/user.py
restcord/user_client.py
restcord/utils.py
restcord/voice.py
restcord/voice_client.py
restcord/webhook.py
restcord/webhook_client.py
restcord.py-0.0.6.dist-info/LICENSE
restcord.py-0.0.6.dist-info/METADATA
restcord.py-0.0.6.dist-info/WHEEL
restcord.py-0.0.6.dist-info/top_level.txt
restcord.py-0.0.6.dist-info/RECORD
