Metadata-Version: 2.1
Name: restcord.py
Version: 0.0.6
Summary: An asynchronous Python client for Discord's API
Home-page: https://github.com/Yandawl/restcord.py
Author: Lethys
License: MIT
Keywords: discord rest api python asynchronous
Platform: UNKNOWN
Classifier: Development Status :: 2 - Pre-Alpha
Classifier: License :: OSI Approved :: MIT License
Classifier: Intended Audience :: Developers
Classifier: Natural Language :: English
Classifier: Operating System :: OS Independent
Classifier: Programming Language :: Python :: 3.7
Classifier: Programming Language :: Python :: 3.8
Classifier: Topic :: Internet
Classifier: Topic :: Software Development :: Libraries
Classifier: Topic :: Software Development :: Libraries :: Python Modules
Classifier: Topic :: Utilities
Requires-Dist: aiohttp
Requires-Dist: asyncio
